guibot/__init__.py
guibot/calibrator.py
guibot/config.py
guibot/controller.py
guibot/desktopcontrol.py
guibot/errors.py
guibot/fileresolver.py
guibot/finder.py
guibot/guibot.py
guibot/guibot_proxy.py
guibot/guibot_simple.py
guibot/imagelogger.py
guibot/inputmap.py
guibot/location.py
guibot/match.py
guibot/path.py
guibot/region.py
guibot/target.py
guibot-0.51.1.dist-info/METADATA
guibot-0.51.1.dist-info/WHEEL
guibot-0.51.1.dist-info/top_level.txt
guibot-0.51.1.dist-info/RECORD
